utec_logger/__init__.py
utec_logger/logger.py
utec_logger-1.7.dist-info/METADATA
utec_logger-1.7.dist-info/WHEEL
utec_logger-1.7.dist-info/top_level.txt
utec_logger-1.7.dist-info/RECORD
