Metadata-Version: 2.4
Name: utec_logger
Version: 1.7
Summary: UTEC Logger
Author-email: Maykol Morales <maykol.morales@utec.edu.pe>
Requires-Python: >=3.8
Requires-Dist: boto3==1.35.54
Requires-Dist: botocore==1.35.54
Requires-Dist: certifi==2024.8.30
Requires-Dist: charset-normalizer==3.4.0
Requires-Dist: idna==3.10
Requires-Dist: jmespath==1.0.1
Requires-Dist: python-dateutil==2.9.0.post0
Requires-Dist: requests==2.32.3
Requires-Dist: s3transfer==0.10.3
Requires-Dist: six==1.16.0
Requires-Dist: urllib3==2.2.3
